[
    {
        "camp": 1.250513888888889
    },
    {
        "refugee": 1.243076388888889
    },
    {
        "Cox": 1.243076388888889
    },
    {
        "Women": 1.1900458333333335
    },
    {
        "Stories": 1.1900458333333335
    },
    {
        "birth": 1.0587916666666666
    },
    {
        "Bazar": 1.0587916666666666
    },
    {
        "Refugee": 1.0044979166666665
    },
    {
        "Unspeakable": 1.0044979166666665
    },
    {
        "COX": 1.0
    },
    {
        "BAZAR": 1.0
    },
    {
        "Bangladesh": 1.0
    },
    {
        "Oct": 1.0
    },
    {
        "baby": 0.8726180555555555
    },
    {
        "district": 0.8726180555555555
    },
    {
        "Rohingya": 0.80545625
    },
    {
        "Violence": 0.80545625
    },
    {
        "Yasmin": 0.7002569444444444
    },
    {
        "Myanmar": 0.7002569444444444
    },
    {
        "IPS": 0.15000000000000002
    },
    {
        "Taw": 1.1545347222222224
    },
    {
        "houses": 1.1545347222222224
    },
    {
        "Pyin": 1.1292708333333334
    },
    {
        "soldiers": 1.129270833333333
    },
    {
        "village": 1.1066041666666666
    },
    {
        "group": 1.1066041666666666
    },
    {
        "Myanmar": 1.104361111111111
    },
    {
        "Hpaung": 1.006611111111111
    },
    {
        "people": 1.006611111111111
    },
    {
        "home": 0.8545555555555555
    },
    {
        "gunfire": 0.8545555555555555
    },
    {
        "weeks": 0.6962430555555555
    },
    {
        "air": 0.6962430555555555
    },
    {
        "activist": 1.0814583333333332
    },
    {
        "years": 1.0814583333333332
    },
    {
        "level": 1.0814583333333332
    },
    {
        "rights": 0.8778125
    },
    {
        "violence": 0.8778125
    },
    {
        "Chief": 1.3187027777777778
    },
    {
        "month": 1.3187027777777778
    },
    {
        "Sarker": 1.1386916666666667
    },
    {
        "Executive": 1.1386916666666667
    },
    {
        "IPS": 1.1386916666666667
    },
    {
        "pregnancy": 1.1386916666666667
    },
    {
        "Dey": 0.9487166666666667
    },
    {
        "aid": 0.9487166666666667
    },
    {
        "Yasmin": 0.9487166666666667
    },
    {
        "Myanmar": 0.9487166666666667
    },
    {
        "Chandra": 0.7532402777777778
    },
    {
        "organisation": 0.7532402777777778
    },
    {
        "eyes": 0.7532402777777778
    },
    {
        "soldiers": 0.7532402777777778
    },
    {
        "Mukti": 0.15000000000000002
    },
    {
        "Yasmin": 1.0
    },
    {
        "village": 1.0
    },
    {
        "neighbours": 1.0
    },
    {
        "women": 1.0814583333333332
    },
    {
        "children": 1.0814583333333332
    },
    {
        "men": 1.0814583333333332
    },
    {
        "dozen": 0.8778125
    },
    {
        "fear": 0.8778125
    },
    {
        "truck": 1.1900458333333335
    },
    {
        "neighbourhood": 1.1900458333333335
    },
    {
        "army": 1.0044979166666665
    },
    {
        "soldiers": 1.0044979166666665
    },
    {
        "evening": 0.80545625
    },
    {
        "homes": 0.80545625
    },
    {
        "home": 1.0
    },
    {
        "soldiers": 1.0
    },
    {
        "house": 1.0
    },
    {
        "guns": 0.15000000000000002
    },
    {
        "stage": 1.0
    },
    {
        "consciousness": 1.0
    },
    {
        "screams": 1.0
    },
    {
        "ordeal": 1.0
    },
    {
        "state": 1.4780069444444441
    },
    {
        "army": 1.1434374999999997
    },
    {
        "September": 1.1114837962962962
    },
    {
        "raids": 1.0821273148148147
    },
    {
        "minority": 1.024122685185185
    },
    {
        "Buddhist": 1.0232569444444444
    },
    {
        "mobs": 1.0124745370370367
    },
    {
        "Myanmar": 0.9865416666666665
    },
    {
        "home": 0.8725787037037036
    },
    {
        "husband": 0.8411759259259259
    },
    {
        "Rakhine": 0.7352407407407406
    },
    {
        "Yasmin": 0.6895532407407408
    },
    {
        "district": 1.5301743827160492
    },
    {
        "capital": 1.1523572530864197
    },
    {
        "Bangladesh": 1.1337831790123456
    },
    {
        "km": 1.105331790123457
    },
    {
        "Bazaar": 1.0512492283950614
    },
    {
        "Dhaka": 0.9905555555555555
    },
    {
        "Cox": 0.9006496913580246
    },
    {
        "Rohingya": 0.8411759259259259
    },
    {
        "camps": 0.6895532407407408
    },
    {
        "Bandarban": 0.6051697530864197
    },
    {
        "locals": 1.0
    },
    {
        "strangers": 1.0
    },
    {
        "influxes": 1.0
    },
    {
        "refugees": 1.0
    },
    {
        "Myanmar": 1.0814583333333332
    },
    {
        "Bangladesh": 1.0814583333333332
    },
    {
        "neighbor": 1.0814583333333332
    },
    {
        "Rohingyas": 0.8778125
    },
    {
        "grounds": 0.8778125
    },
    {
        "government": 1.1900458333333335
    },
    {
        "crackdown": 1.1900458333333335
    },
    {
        "exodus": 1.0044979166666665
    },
    {
        "August": 1.0044979166666665
    },
    {
        "Rohingya": 0.80545625
    },
    {
        "world": 0.80545625
    },
    {
        "atrocities": 1.0814583333333332
    },
    {
        "junta": 1.0814583333333332
    },
    {
        "time": 1.0814583333333332
    },
    {
        "magnitude": 0.8778125
    },
    {
        "imagination": 0.8778125
    },
    {
        "persecution": 1.0
    },
    {
        "genocide": 1.0
    },
    {
        "Myanmar": 1.0
    },
    {
        "rulers": 1.0
    },
    {
        "Ra\u2019ad": 1.1545347222222224
    },
    {
        "Rohingya": 1.1545347222222224
    },
    {
        "Al": 1.1252569444444442
    },
    {
        "soldiers": 1.1252569444444442
    },
    {
        "Hussein": 1.0885416666666665
    },
    {
        "assaults": 1.0885416666666665
    },
    {
        "United": 1.0521805555555555
    },
    {
        "junta": 1.0521805555555555
    },
    {
        "Nations": 1.0180625
    },
    {
        "rights": 1.0180624999999996
    },
    {
        "commissioner": 1.0080277777777777
    },
    {
        "Zeid": 1.006611111111111
    },
    {
        "women": 1.006611111111111
    },
    {
        "cleansing": 0.8545555555555555
    },
    {
        "killings": 0.8545555555555555
    },
    {
        "violence": 0.6962430555555555
    },
    {
        "men": 0.6962430555555555
    },
    {
        "reasoning": 1.0
    },
    {
        "homes": 1.0
    },
    {
        "Rohingya": 1.3187027777777778
    },
    {
        "state": 1.1386916666666667
    },
    {
        "population": 1.1386916666666667
    },
    {
        "Rakhine": 0.9487166666666667
    },
    {
        "Myanmar": 0.9487166666666667
    },
    {
        "operation": 0.7532402777777778
    },
    {
        "citizens": 0.7532402777777778
    },
    {
        "women": 1.4512870370370368
    },
    {
        "Rohingya": 1.4218649691358025
    },
    {
        "headache": 1.0220895061728394
    },
    {
        "border": 1.0173804012345677
    },
    {
        "-": 1.0074243827160494
    },
    {
        "mid": 0.999488425925926
    },
    {
        "men": 0.9967731481481481
    },
    {
        "IPS": 0.9958680555555555
    },
    {
        "September": 0.9938086419753087
    },
    {
        "Bangladesh": 0.8814984567901234
    },
    {
        "junta": 0.8743364197530864
    },
    {
        "man": 0.7441604938271604
    },
    {
        "criticism": 0.594020061728395
    },
    {
        "women": 1.0814583333333332
    },
    {
        "children": 1.0814583333333332
    },
    {
        "assault": 1.0814583333333332
    },
    {
        "strategy": 0.8778125
    },
    {
        "abuse": 0.8778125
    },
    {
        "Nations": 1.1545347222222224
    },
    {
        "supply": 1.1545347222222224
    },
    {
        "NGOs": 1.1252569444444442
    },
    {
        "water": 1.1252569444444442
    },
    {
        "ground": 1.0885416666666665
    },
    {
        "shelters": 1.0885416666666665
    },
    {
        "emergency": 1.0521805555555555
    },
    {
        "distribution": 1.0521805555555555
    },
    {
        "services": 1.0220763888888889
    },
    {
        "food": 1.0220763888888889
    },
    {
        "United": 1.006611111111111
    },
    {
        "latrines": 1.006611111111111
    },
    {
        "agencies": 0.8545555555555555
    },
    {
        "course": 0.8545555555555555
    },
    {
        "IPS": 0.6962430555555555
    },
    {
        "healthcare": 0.6962430555555555
    },
    {
        "level": 1.3187027777777778
    },
    {
        "experiences": 1.1386916666666667
    },
    {
        "abuse": 1.1386916666666667
    },
    {
        "woman": 0.9487166666666667
    },
    {
        "gang": 0.9487166666666667
    },
    {
        "correspondent": 0.7532402777777778
    },
    {
        "rape": 0.7532402777777778
    },
    {
        "women": 1.3187027777777778
    },
    {
        "stories": 1.1386916666666667
    },
    {
        "girls": 1.1386916666666667
    },
    {
        "witnesses": 0.9487166666666667
    },
    {
        "family": 0.9487166666666667
    },
    {
        "Survivors": 0.7532402777777778
    },
    {
        "members": 0.7532402777777778
    },
    {
        "soldiers": 0.15000000000000002
    },
    {
        "children": 1.1900458333333335
    },
    {
        "killings": 1.1900458333333335
    },
    {
        "mercy": 1.0044979166666665
    },
    {
        "burning": 1.0044979166666665
    },
    {
        "soldiers": 0.80545625
    },
    {
        "homes": 0.80545625
    },
    {
        "Sarker": 1.1545347222222224
    },
    {
        "activist": 1.1545347222222224
    },
    {
        "Chief": 1.1252569444444442
    },
    {
        "rights": 1.1252569444444442
    },
    {
        "Executive": 1.0885416666666665
    },
    {
        "IPS": 1.0885416666666665
    },
    {
        "Mukti": 1.0521805555555555
    },
    {
        "Bazaar": 1.0521805555555555
    },
    {
        "NGO": 1.0220763888888889
    },
    {
        "Cox": 1.0220763888888889
    },
    {
        "Dey": 1.006611111111111
    },
    {
        "years": 1.006611111111111
    },
    {
        "Chandra": 0.8545555555555555
    },
    {
        "level": 0.8545555555555555
    },
    {
        "Bimol": 0.6962430555555555
    },
    {
        "violence": 0.6962430555555555
    },
    {
        "women": 1.0
    },
    {
        "camps": 1.0
    },
    {
        "tales": 1.0
    },
    {
        "abuse": 1.0
    },
    {
        "movie": 0.15000000000000002
    },
    {
        "CODEC": 1.1585486111111112
    },
    {
        "Stories": 1.1585486111111112
    },
    {
        "NGO": 1.1433194444444443
    },
    {
        "IPS": 1.1433194444444443
    },
    {
        "Cox": 1.1407222222222222
    },
    {
        "Bazaar": 1.1407222222222222
    },
    {
        "person": 1.006611111111111
    },
    {
        "abuse": 1.006611111111111
    },
    {
        "Fatema": 0.8545555555555555
    },
    {
        "Rohingya": 0.8545555555555555
    },
    {
        "Kaniz": 0.6962430555555555
    },
    {
        "women": 0.6962430555555555
    },
    {
        "women": 1.0
    },
    {
        "incidents": 1.0
    },
    {
        "nightmares": 1.0
    },
    {
        "violence": 1.0
    },
    {
        "world": 1.0
    },
    {
        "today": 1.0
    },
    {
        "women": 0.15000000000000002
    },
    {
        "stories": 1.0814583333333332
    },
    {
        "abuses": 1.0814583333333332
    },
    {
        "corner": 1.0814583333333332
    },
    {
        "Bangladesh": 0.8778125
    },
    {
        "camps": 0.8778125
    },
    {
        "Bazar": 1.1545347222222224
    },
    {
        "Rohingya": 1.1545347222222224
    },
    {
        "district": 1.1252569444444442
    },
    {
        "treatment": 1.1252569444444442
    },
    {
        "hospital": 1.0925555555555555
    },
    {
        "emergency": 1.0925555555555555
    },
    {
        "IPS": 1.0702430555555555
    },
    {
        "beginning": 1.0702430555555555
    },
    {
        "Cox": 1.006611111111111
    },
    {
        "refugees": 1.006611111111111
    },
    {
        "officer": 0.8545555555555555
    },
    {
        "bullet": 0.8545555555555555
    },
    {
        "health": 0.6962430555555555
    },
    {
        "wounds": 0.6962430555555555
    },
    {
        "crisis": 1.0
    },
    {
        "women": 1.0
    },
    {
        "women": 1.0
    },
    {
        "day": 1.0
    },
    {
        "shortages": 1.0
    },
    {
        "beds": 1.0
    },
    {
        "women": 0.15000000000000002
    },
    {
        "women": 1.4966597222222222
    },
    {
        "marks": 1.2452013888888889
    },
    {
        "wounds": 1.0086770833333334
    },
    {
        "rape": 1.0086770833333334
    },
    {
        "hospital": 0.8384999999999999
    },
    {
        "encounters": 0.7751041666666666
    },
    {
        "nurse": 0.6271805555555555
    },
    {
        "women": 0.15000000000000002
    },
    {
        "days": 1.0
    },
    {
        "suffering": 1.0
    },
    {
        "agonies": 1.0
    },
    {
        "healthcare": 1.1545347222222224
    },
    {
        "torture": 1.1545347222222224
    },
    {
        "services": 1.1252569444444442
    },
    {
        "women": 1.1252569444444442
    },
    {
        "Bandarban": 1.0885416666666665
    },
    {
        "tales": 1.0885416666666665
    },
    {
        "Cox": 1.0521805555555555
    },
    {
        "workers": 1.0521805555555555
    },
    {
        "Bazaar": 1.0220763888888889
    },
    {
        "aid": 1.0220763888888889
    },
    {
        "reproductive": 1.006611111111111
    },
    {
        "gang": 1.006611111111111
    },
    {
        "emergency": 0.8545555555555555
    },
    {
        "rape": 0.8545555555555555
    },
    {
        "UNFPA": 0.6962430555555555
    },
    {
        "gunpoint": 0.6962430555555555
    },
    {
        "Bandarban": 1.281397222222222
    },
    {
        "girl": 1.281397222222222
    },
    {
        "Ukhia": 1.0959555555555553
    },
    {
        "father": 1.0959555555555553
    },
    {
        "worker": 0.9075388888888888
    },
    {
        "mother": 0.9075388888888888
    },
    {
        "field": 0.7151083333333333
    },
    {
        "brother": 0.7151083333333333
    },
    {
        "soldiers": 1.0
    },
    {
        "men": 1.0
    },
    {
        "courtyard": 1.0
    },
    {
        "capital": 1.281397222222222
    },
    {
        "Rohingya": 1.281397222222222
    },
    {
        "reporter": 1.0959555555555553
    },
    {
        "camps": 1.0959555555555553
    },
    {
        "Mahmud": 0.9075388888888888
    },
    {
        "victims": 0.9075388888888888
    },
    {
        "Faisal": 0.7151083333333333
    },
    {
        "rape": 0.7151083333333333
    },
    {
        "brutality": 0.15000000000000002
    },
    {
        "fear": 1.0
    },
    {
        "faces": 1.0
    },
    {
        "dialect": 1.0
    },
    {
        "translator": 1.0
    },
    {
        "tales": 1.0
    },
    {
        "gang": 1.0
    },
    {
        "mines": 1.250513888888889
    },
    {
        "forests": 1.243076388888889
    },
    {
        "Myanmar": 1.243076388888889
    },
    {
        "Hossain": 1.0587916666666666
    },
    {
        "border": 1.0587916666666666
    },
    {
        "Jamil": 0.8726180555555555
    },
    {
        "guards": 0.8726180555555555
    },
    {
        "Mohammad": 0.7002569444444444
    },
    {
        "men": 0.7002569444444444
    },
    {
        "member": 1.0814583333333332
    },
    {
        "Rohingya": 1.0814583333333332
    },
    {
        "population": 1.0814583333333332
    },
    {
        "cleansing": 0.8778125
    },
    {
        "country": 0.8778125
    },
    {
        "world": 1.0
    },
    {
        "killings": 1.0
    },
    {
        "women": 1.7165775462962962
    },
    {
        "Bangladesh": 1.4158506944444444
    },
    {
        "member": 1.100622685185185
    },
    {
        "Naripokkho": 1.0710891203703705
    },
    {
        "founder": 0.970761574074074
    },
    {
        "NGO": 0.9692465277777776
    },
    {
        "numbers": 0.942861111111111
    },
    {
        "IPS": 0.9339282407407407
    },
    {
        "rights": 0.9324525462962961
    },
    {
        "people": 0.9246412037037037
    },
    {
        "Huq": 0.823113425925926
    },
    {
        "children": 0.8191388888888889
    },
    {
        "Myanmar": 0.6981909722222222
    },
    {
        "Shireen": 0.681525462962963
    },
    {
        "murder": 1.250513888888889
    },
    {
        "rape": 1.243076388888889
    },
    {
        "arson": 1.243076388888889
    },
    {
        "mass": 1.0587916666666666
    },
    {
        "brutality": 1.0587916666666666
    },
    {
        "atrocities": 0.8726180555555555
    },
    {
        "state": 0.8726180555555555
    },
    {
        "media": 0.7002569444444444
    },
    {
        "Rakhain": 0.7002569444444444
    },
    {
        "Porir": 1.281397222222222
    },
    {
        "Dwip": 1.281397222222222
    },
    {
        "Shah": 1.0959555555555553
    },
    {
        "state": 1.0959555555555553
    },
    {
        "Nayapara": 0.9075388888888888
    },
    {
        "shock": 0.9075388888888888
    },
    {
        "Women": 0.7151083333333333
    },
    {
        "fatigue": 0.7151083333333333
    },
    {
        "julum": 1.0
    },
    {
        "word": 1.0
    },
    {
        "torture": 1.0
    },
    {
        "rape": 1.0
    },
    {
        "military": 0.15000000000000002
    },
    {
        "care": 1.0
    },
    {
        "refugees": 1.0
    },
    {
        "violence": 1.0
    },
    {
        "psycho": 1.0814583333333332
    },
    {
        "counseling": 1.0814583333333332
    },
    {
        "abortion": 1.0814583333333332
    },
    {
        "care": 0.8778125
    },
    {
        "services": 0.8778125
    },
    {
        "Rohingya": 1.0814583333333332
    },
    {
        "refugee": 1.0814583333333332
    },
    {
        "camps": 1.0814583333333332
    },
    {
        "Agencies": 0.8778125
    },
    {
        "women": 0.8778125
    },
    {
        "deliveries": 1.0
    },
    {
        "place": 1.0
    },
    {
        "health": 1.1900458333333335
    },
    {
        "services": 1.1900458333333335
    },
    {
        "emergency": 1.0044979166666665
    },
    {
        "situation": 1.0044979166666665
    },
    {
        "clock": 0.80545625
    },
    {
        "Shireen": 0.80545625
    },
    {
        "majority": 1.1900458333333335
    },
    {
        "country": 1.1900458333333335
    },
    {
        "Buddhist": 1.0044979166666665
    },
    {
        "Bangladesh": 1.0044979166666665
    },
    {
        "Rohingya": 0.80545625
    },
    {
        "August": 0.80545625
    },
    {
        "Cox": 1.2137986111111108
    },
    {
        "Bazar": 1.2137986111111108
    },
    {
        "Teknaf": 1.2067152777777777
    },
    {
        "district": 1.2067152777777777
    },
    {
        "road": 1.024673611111111
    },
    {
        "Myanmar": 1.024673611111111
    },
    {
        "settlements": 0.8585694444444444
    },
    {
        "Naf": 0.8585694444444444
    },
    {
        "refugee": 0.6962430555555555
    },
    {
        "river": 0.6962430555555555
    },
    {
        "International": 1.3187027777777778
    },
    {
        "day": 1.1386916666666667
    },
    {
        "Organisation": 1.1386916666666667
    },
    {
        "camps": 0.9487166666666667
    },
    {
        "Migration": 0.9487166666666667
    },
    {
        "refugees": 0.7532402777777778
    },
    {
        "IOM": 0.7532402777777778
    },
    {
        "community": 1.0814583333333332
    },
    {
        "dollars": 1.0814583333333332
    },
    {
        "February": 1.0814583333333332
    },
    {
        "IOM": 0.8778125
    },
    {
        "crisis": 0.8778125
    },
    {
        "safety": 1.1545347222222224
    },
    {
        "Director": 1.1545347222222224
    },
    {
        "protection": 1.1252569444444442
    },
    {
        "IOM": 1.1252569444444442
    },
    {
        "Cox": 1.0885416666666665
    },
    {
        "Swing": 1.0885416666666665
    },
    {
        "Bazar": 1.0561944444444444
    },
    {
        "Lacy": 1.0561944444444444
    },
    {
        "William": 1.036125
    },
    {
        "belief": 1.006611111111111
    },
    {
        "General": 1.006611111111111
    },
    {
        "Rakhine": 0.8545555555555555
    },
    {
        "statement": 0.8545555555555555
    },
    {
        "refugees": 0.6962430555555555
    },
    {
        "October": 0.6962430555555555
    },
    {
        "responsibility": 1.0
    },
    {
        "suffering": 1.0
    },
    {
        "trauma": 1.0
    },
    {
        "way": 1.0
    },
    {
        "refugees": 1.1900458333333335
    },
    {
        "forest": 1.1900458333333335
    },
    {
        "thousands": 1.0044979166666665
    },
    {
        "Bangladesh": 1.0044979166666665
    },
    {
        "witnesses": 0.80545625
    },
    {
        "border": 0.80545625
    },
    {
        "hilltops": 1.0
    },
    {
        "belongings": 1.0
    },
    {
        "United": 1.1545347222222224
    },
    {
        "tarpaulins": 1.1545347222222224
    },
    {
        "Nations": 1.1252569444444442
    },
    {
        "thousands": 1.1252569444444442
    },
    {
        "High": 1.0885416666666665
    },
    {
        "refugees": 1.0885416666666665
    },
    {
        "Commissioner": 1.0521805555555555
    },
    {
        "camp": 1.0521805555555555
    },
    {
        "Refugees": 1.0180625
    },
    {
        "Reuters": 1.0180625
    },
    {
        "Myanmar": 1.006611111111111
    },
    {
        "hills": 1.006611111111111
    },
    {
        "Filippo": 1.0040138888888888
    },
    {
        "Grandi": 1.0040138888888888
    },
    {
        "people": 0.8545555555555555
    },
    {
        "rice": 0.8545555555555555
    },
    {
        "fear": 0.6962430555555555
    },
    {
        "paddies": 0.6962430555555555
    },
    {
        "families": 1.0814583333333332
    },
    {
        "wounds": 1.0814583333333332
    },
    {
        "rapes": 1.0814583333333332
    },
    {
        "Parents": 0.8778125
    },
    {
        "women": 0.8778125
    },
    {
        "people": 1.3187027777777778
    },
    {
        "time": 1.1386916666666667
    },
    {
        "wounds": 1.1386916666666667
    },
    {
        "violence": 0.9487166666666667
    },
    {
        "needs": 0.9487166666666667
    },
    {
        "lot": 0.7532402777777778
    },
    {
        "Grandi": 0.7532402777777778
    }
]