[
    {
        "cause": 1.0814583333333332
    },
    {
        "fire": 1.0814583333333332
    },
    {
        "warehouse": 1.0814583333333332
    },
    {
        "Garda\u00ed": 0.8778125
    },
    {
        "Dublin": 0.8778125
    },
    {
        "afternoon": 1.281397222222222
    },
    {
        "premises": 1.281397222222222
    },
    {
        "yesterday": 1.0959555555555553
    },
    {
        "Richmond": 1.0959555555555553
    },
    {
        "pm": 0.9075388888888888
    },
    {
        "Road": 0.9075388888888888
    },
    {
        "blaze": 0.7151083333333333
    },
    {
        "Drumcondra": 0.7151083333333333
    },
    {
        "Brigade": 1.3187027777777778
    },
    {
        "Fire": 1.1386916666666667
    },
    {
        "scene": 1.1386916666666667
    },
    {
        "Dublin": 0.9487166666666667
    },
    {
        "hours": 0.9487166666666667
    },
    {
        "units": 0.7532402777777778
    },
    {
        "fire": 0.7532402777777778
    },
    {
        "warehouse": 1.0
    },
    {
        "garda\u00ed": 1.0
    },
    {
        "bonfires": 1.250513888888889
    },
    {
        "Brigade": 1.243076388888889
    },
    {
        "railway": 1.243076388888889
    },
    {
        "Fire": 1.0587916666666666
    },
    {
        "lines": 1.0587916666666666
    },
    {
        "Dublin": 0.8726180555555555
    },
    {
        "Baldoyle": 0.8726180555555555
    },
    {
        "Units": 0.7002569444444444
    },
    {
        "Kilbarrack": 0.7002569444444444
    }
]